powerbi_push_datasets.py
powerbi_push_datasets-0.1a5.dist-info/LICENSE
powerbi_push_datasets-0.1a5.dist-info/METADATA
powerbi_push_datasets-0.1a5.dist-info/WHEEL
powerbi_push_datasets-0.1a5.dist-info/top_level.txt
powerbi_push_datasets-0.1a5.dist-info/RECORD
