Metadata-Version: 2.1
Name: powerbi-push-datasets
Version: 0.1a5
Summary: Power BI Push Datasets Mgmt
Home-page: https://github.com/DataBooster/PyWebApi
Author: Abel Cheng
Author-email: abelcys@gmail.com
License: MIT
Keywords: PowerBI,Push,Datasets,REST,API,Tabular,Model,ResultSets,StoredProcedure,TabularEditor,metadata,schema,table,workspace,pump,xcopy
Platform: any
Requires-Python: >=3.6
Requires-Dist: simple-rest-call
